<?xml version="1.0" encoding="utf-8"?>
<Script xmlns:xsi="http://www.w3.org/2001/XMLSchema-instance" xmlns:xsd="http://www.w3.org/2001/XMLSchema">
  <Commands>
    <ScriptAction>
      <ScriptCommand xsi:type="CommentCommand" CommandID="3801a123-0f0c-4c70-a049-5b3c3104d1b3" CommandName="CommentCommand" IsCommented="false" SelectionName="Add Code Comment" DefaultPause="0" LineNumber="1" PauseBeforeExeucution="false" v_Comment="Check List Item Exists Sample" CommandEnabled="true" />
    </ScriptAction>
    <ScriptAction>
      <ScriptCommand xsi:type="CommentCommand" CommandID="3801a123-0f0c-4c70-a049-5b3c3104d1b3" CommandName="CommentCommand" IsCommented="false" SelectionName="Add Code Comment" DefaultPause="0" LineNumber="2" PauseBeforeExeucution="false" v_Comment="Create List, now ⦃ &quot;abc&quot;, &quot;def&quot; ⦄" CommandEnabled="true" />
    </ScriptAction>
    <ScriptAction>
      <ScriptCommand xsi:type="CreateListCommand" CommandID="630ceffa-7f97-44d4-b16b-6ec8e9f7d041" CommandName="CreateListCommand" IsCommented="false" SelectionName="Create List" DefaultPause="0" LineNumber="3" PauseBeforeExeucution="false" CommandEnabled="true" v_ListName="vList">
        <v_ListValues>
          <xs:schema id="NewDataSet" xmlns="" xmlns:xs="http://www.w3.org/2001/XMLSchema" xmlns:msdata="urn:schemas-microsoft-com:xml-msdata">
            <xs:element name="ListValues122921.033024">
              <xs:complexType>
                <xs:sequence>
                  <xs:element name="Values" type="xs:string" minOccurs="0" />
                </xs:sequence>
              </xs:complexType>
            </xs:element>
            <xs:element name="NewDataSet" msdata:IsDataSet="true" msdata:MainDataTable="ListValues122921.033024" msdata:UseCurrentLocale="true">
              <xs:complexType>
                <xs:choice minOccurs="0" maxOccurs="unbounded">
                  <xs:element ref="ListValues122921.033024" />
                </xs:choice>
              </xs:complexType>
            </xs:element>
          </xs:schema>
          <diffgr:diffgram xmlns:msdata="urn:schemas-microsoft-com:xml-msdata" xmlns:diffgr="urn:schemas-microsoft-com:xml-diffgram-v1">
            <DocumentElement>
              <ListValues122921.033024 diffgr:id="ListValues122921.0330241" msdata:rowOrder="0" diffgr:hasChanges="modified">
                <Values>abc</Values>
              </ListValues122921.033024>
              <ListValues122921.033024 diffgr:id="ListValues122921.0330242" msdata:rowOrder="1" diffgr:hasChanges="modified">
                <Values>def</Values>
              </ListValues122921.033024>
            </DocumentElement>
            <diffgr:before>
              <ListValues122921.033024 diffgr:id="ListValues122921.0330241" msdata:rowOrder="0">
                <Values>abc</Values>
              </ListValues122921.033024>
              <ListValues122921.033024 diffgr:id="ListValues122921.0330242" msdata:rowOrder="1">
                <Values>def</Values>
              </ListValues122921.033024>
            </diffgr:before>
          </diffgr:diffgram>
        </v_ListValues>
      </ScriptCommand>
    </ScriptAction>
    <ScriptAction>
      <ScriptCommand xsi:type="CommentCommand" CommandID="3801a123-0f0c-4c70-a049-5b3c3104d1b3" CommandName="CommentCommand" IsCommented="false" SelectionName="Add Code Comment" DefaultPause="0" LineNumber="4" PauseBeforeExeucution="false" v_Comment="Search &quot;def&quot;" CommandEnabled="true" />
    </ScriptAction>
    <ScriptAction>
      <ScriptCommand xsi:type="CheckListItemExistsCommand" CommandID="4a70ef10-8446-42da-b8e7-5a52859d4c7b" CommandName="CheckListItemExistsCommand" IsCommented="false" SelectionName="Check List Item Exists" DefaultPause="0" LineNumber="5" PauseBeforeExeucution="false" CommandEnabled="true" v_ListName="vList" v_SearchItem="def" v_Result="vResult" />
    </ScriptAction>
    <ScriptAction>
      <ScriptCommand xsi:type="BeginIfCommand" CommandID="6b7f2bf1-8252-4855-8c1e-61ee8bb42cd4" CommandName="BeginIfCommand" IsCommented="false" SelectionName="Begin If" DefaultPause="0" LineNumber="6" PauseBeforeExeucution="false" CommandEnabled="true" v_IfActionType="Boolean">
        <v_IfActionParameterTable>
          <xs:schema id="NewDataSet" xmlns="" xmlns:xs="http://www.w3.org/2001/XMLSchema" xmlns:msdata="urn:schemas-microsoft-com:xml-msdata">
            <xs:element name="I3Ac午ionPara37Table122921.033751">
              <xs:complexType>
                <xs:sequence>
                  <xs:element name="Parameter_x0020_Name" type="xs:string" minOccurs="0" />
                  <xs:element name="Parameter_x0020_Value" type="xs:string" minOccurs="0" />
                </xs:sequence>
              </xs:complexType>
            </xs:element>
            <xs:element name="NewDataSet" msdata:IsDataSet="true" msdata:MainDataTable="I3Ac午ionPara37Table122921.033751" msdata:UseCurrentLocale="true">
              <xs:complexType>
                <xs:choice minOccurs="0" maxOccurs="unbounded">
                  <xs:element ref="I3Ac午ionPara37Table122921.033751" />
                </xs:choice>
              </xs:complexType>
            </xs:element>
          </xs:schema>
          <diffgr:diffgram xmlns:msdata="urn:schemas-microsoft-com:xml-msdata" xmlns:diffgr="urn:schemas-microsoft-com:xml-diffgram-v1">
            <DocumentElement>
              <I3Ac午ionPara37Table122921.033751 diffgr:id="I3Ac午ionPara37Table122921.0337511" msdata:rowOrder="0" diffgr:hasChanges="modified">
                <Parameter_x0020_Name>Variable Name</Parameter_x0020_Name>
                <Parameter_x0020_Value>⦃vResult⦄</Parameter_x0020_Value>
              </I3Ac午ionPara37Table122921.033751>
              <I3Ac午ionPara37Table122921.033751 diffgr:id="I3Ac午ionPara37Table122921.0337512" msdata:rowOrder="1" diffgr:hasChanges="modified">
                <Parameter_x0020_Name>Value Is</Parameter_x0020_Name>
                <Parameter_x0020_Value>True</Parameter_x0020_Value>
              </I3Ac午ionPara37Table122921.033751>
            </DocumentElement>
            <diffgr:before>
              <I3Ac午ionPara37Table122921.033751 diffgr:id="I3Ac午ionPara37Table122921.0337511" msdata:rowOrder="0">
                <Parameter_x0020_Name>Variable Name</Parameter_x0020_Name>
                <Parameter_x0020_Value>{vResult}</Parameter_x0020_Value>
              </I3Ac午ionPara37Table122921.033751>
              <I3Ac午ionPara37Table122921.033751 diffgr:id="I3Ac午ionPara37Table122921.0337512" msdata:rowOrder="1">
                <Parameter_x0020_Name>Value Is</Parameter_x0020_Name>
                <Parameter_x0020_Value>True</Parameter_x0020_Value>
              </I3Ac午ionPara37Table122921.033751>
            </diffgr:before>
          </diffgr:diffgram>
        </v_IfActionParameterTable>
      </ScriptCommand>
      <AdditionalScriptCommands>
        <ScriptCommand xsi:type="MessageBoxCommand" CommandID="530990a2-d547-43ba-9ecf-19887d635c69" CommandName="MessageBoxCommand" IsCommented="false" SelectionName="Show Message" DefaultPause="0" LineNumber="7" PauseBeforeExeucution="false" CommandEnabled="true" v_Message="List has &quot;def&quot;" v_AutoCloseAfter="0" />
      </AdditionalScriptCommands>
      <AdditionalScriptCommands>
        <ScriptCommand xsi:type="ElseCommand" CommandID="a1a49bf5-dc59-4cd7-9d7f-0a69130f80ea" CommandName="ElseCommand" IsCommented="false" SelectionName="Else" DefaultPause="0" LineNumber="8" PauseBeforeExeucution="false" CommandEnabled="true" />
      </AdditionalScriptCommands>
      <AdditionalScriptCommands>
        <ScriptCommand xsi:type="MessageBoxCommand" CommandID="530990a2-d547-43ba-9ecf-19887d635c69" CommandName="MessageBoxCommand" IsCommented="false" SelectionName="Show Message" DefaultPause="0" LineNumber="9" PauseBeforeExeucution="false" CommandEnabled="true" v_Message="&quot;def&quot; does not exists in List" v_AutoCloseAfter="0" />
      </AdditionalScriptCommands>
      <AdditionalScriptCommands>
        <ScriptCommand xsi:type="EndIfCommand" CommandID="eddac332-3352-41ca-a9ee-d43d885e532b" CommandName="EndIfCommand" IsCommented="false" SelectionName="End If" DefaultPause="0" LineNumber="10" PauseBeforeExeucution="false" CommandEnabled="true" />
      </AdditionalScriptCommands>
    </ScriptAction>
    <ScriptAction>
      <ScriptCommand xsi:type="CommentCommand" CommandID="3801a123-0f0c-4c70-a049-5b3c3104d1b3" CommandName="CommentCommand" IsCommented="false" SelectionName="Add Code Comment" DefaultPause="0" LineNumber="11" PauseBeforeExeucution="false" v_Comment="Search &quot;hello&quot;" CommandEnabled="true" />
    </ScriptAction>
    <ScriptAction>
      <ScriptCommand xsi:type="CheckListItemExistsCommand" CommandID="4a70ef10-8446-42da-b8e7-5a52859d4c7b" CommandName="CheckListItemExistsCommand" IsCommented="false" SelectionName="Check List Item Exists" DefaultPause="0" LineNumber="12" PauseBeforeExeucution="false" CommandEnabled="true" v_ListName="vList" v_SearchItem="hello" v_Result="vResult" />
    </ScriptAction>
    <ScriptAction>
      <ScriptCommand xsi:type="BeginIfCommand" CommandID="6b7f2bf1-8252-4855-8c1e-61ee8bb42cd4" CommandName="BeginIfCommand" IsCommented="false" SelectionName="Begin If" DefaultPause="0" LineNumber="13" PauseBeforeExeucution="false" CommandEnabled="true" v_IfActionType="Boolean">
        <v_IfActionParameterTable>
          <xs:schema id="NewDataSet" xmlns="" xmlns:xs="http://www.w3.org/2001/XMLSchema" xmlns:msdata="urn:schemas-microsoft-com:xml-msdata">
            <xs:element name="I3Ac午ionPara37Table122921.033751">
              <xs:complexType>
                <xs:sequence>
                  <xs:element name="Parameter_x0020_Name" type="xs:string" minOccurs="0" />
                  <xs:element name="Parameter_x0020_Value" type="xs:string" minOccurs="0" />
                </xs:sequence>
              </xs:complexType>
            </xs:element>
            <xs:element name="NewDataSet" msdata:IsDataSet="true" msdata:MainDataTable="I3Ac午ionPara37Table122921.033751" msdata:UseCurrentLocale="true">
              <xs:complexType>
                <xs:choice minOccurs="0" maxOccurs="unbounded">
                  <xs:element ref="I3Ac午ionPara37Table122921.033751" />
                </xs:choice>
              </xs:complexType>
            </xs:element>
          </xs:schema>
          <diffgr:diffgram xmlns:msdata="urn:schemas-microsoft-com:xml-msdata" xmlns:diffgr="urn:schemas-microsoft-com:xml-diffgram-v1">
            <DocumentElement>
              <I3Ac午ionPara37Table122921.033751 diffgr:id="I3Ac午ionPara37Table122921.0337511" msdata:rowOrder="0" diffgr:hasChanges="modified">
                <Parameter_x0020_Name>Variable Name</Parameter_x0020_Name>
                <Parameter_x0020_Value>⦃vResult⦄</Parameter_x0020_Value>
              </I3Ac午ionPara37Table122921.033751>
              <I3Ac午ionPara37Table122921.033751 diffgr:id="I3Ac午ionPara37Table122921.0337512" msdata:rowOrder="1" diffgr:hasChanges="modified">
                <Parameter_x0020_Name>Value Is</Parameter_x0020_Name>
                <Parameter_x0020_Value>True</Parameter_x0020_Value>
              </I3Ac午ionPara37Table122921.033751>
            </DocumentElement>
            <diffgr:before>
              <I3Ac午ionPara37Table122921.033751 diffgr:id="I3Ac午ionPara37Table122921.0337511" msdata:rowOrder="0">
                <Parameter_x0020_Name>Variable Name</Parameter_x0020_Name>
                <Parameter_x0020_Value>{vResult}</Parameter_x0020_Value>
              </I3Ac午ionPara37Table122921.033751>
              <I3Ac午ionPara37Table122921.033751 diffgr:id="I3Ac午ionPara37Table122921.0337512" msdata:rowOrder="1">
                <Parameter_x0020_Name>Value Is</Parameter_x0020_Name>
                <Parameter_x0020_Value>True</Parameter_x0020_Value>
              </I3Ac午ionPara37Table122921.033751>
            </diffgr:before>
          </diffgr:diffgram>
        </v_IfActionParameterTable>
      </ScriptCommand>
      <AdditionalScriptCommands>
        <ScriptCommand xsi:type="MessageBoxCommand" CommandID="530990a2-d547-43ba-9ecf-19887d635c69" CommandName="MessageBoxCommand" IsCommented="false" SelectionName="Show Message" DefaultPause="0" LineNumber="14" PauseBeforeExeucution="false" CommandEnabled="true" v_Message="List has &quot;hello&quot;" v_AutoCloseAfter="0" />
      </AdditionalScriptCommands>
      <AdditionalScriptCommands>
        <ScriptCommand xsi:type="ElseCommand" CommandID="a1a49bf5-dc59-4cd7-9d7f-0a69130f80ea" CommandName="ElseCommand" IsCommented="false" SelectionName="Else" DefaultPause="0" LineNumber="15" PauseBeforeExeucution="false" CommandEnabled="true" />
      </AdditionalScriptCommands>
      <AdditionalScriptCommands>
        <ScriptCommand xsi:type="MessageBoxCommand" CommandID="530990a2-d547-43ba-9ecf-19887d635c69" CommandName="MessageBoxCommand" IsCommented="false" SelectionName="Show Message" DefaultPause="0" LineNumber="16" PauseBeforeExeucution="false" CommandEnabled="true" v_Message="&quot;hello&quot; does not exists in List" v_AutoCloseAfter="0" />
      </AdditionalScriptCommands>
      <AdditionalScriptCommands>
        <ScriptCommand xsi:type="EndIfCommand" CommandID="eddac332-3352-41ca-a9ee-d43d885e532b" CommandName="EndIfCommand" IsCommented="false" SelectionName="End If" DefaultPause="0" LineNumber="17" PauseBeforeExeucution="false" CommandEnabled="true" />
      </AdditionalScriptCommands>
    </ScriptAction>
  </Commands>
  <Info>
    <TasktVersion>3.5.0.55</TasktVersion>
    <Author />
    <LastRunTime>2021-12-29T15:40:18.2299594+09:00</LastRunTime>
    <RunTimes>6</RunTimes>
    <ScriptVersion>0.0.0</ScriptVersion>
    <Description />
  </Info>
  <Variables>
    <ScriptVariable>
      <VariableName>vList</VariableName>
      <VariableValue xsi:type="xsd:string"></VariableValue>
    </ScriptVariable>
    <ScriptVariable>
      <VariableName>vResult</VariableName>
      <VariableValue xsi:type="xsd:string"></VariableValue>
    </ScriptVariable>
  </Variables>
</Script>