<?xml version="1.0" encoding="utf-8"?>
<!--
Copyright (c) 2017 Jason Bayldon

Licensed under the Apache License, Version 2.0 (the "License");
you may not use this file except in compliance with the License.
You may obtain a copy of the License at

    http://www.apache.org/licenses/LICENSE-2.0

Unless required by applicable law or agreed to in writing, software
distributed under the License is distributed on an "AS IS" BASIS,
WITHOUT WARRANTIES OR CONDITIONS OF ANY KIND, either express or implied.
See the License for the specific language governing permissions and
limitations under the License.
-->
<Script xmlns:xsi="http://www.w3.org/2001/XMLSchema-instance" xmlns:xsd="http://www.w3.org/2001/XMLSchema">
  <Commands>
    <ScriptAction>
      <ScriptCommand xsi:type="VariableCommand" CommandName="VariableCommand" IsCommented="false" SelectionName="Variable - Set Variable" DefaultPause="250" LineNumber="1" PauseBeforeExeucution="false" CommandEnabled="true" v_userVariableName="ScouterPowerLevel" v_Input="9000" />
    </ScriptAction>
    <ScriptAction>
      <ScriptCommand xsi:type="BeginIfCommand" CommandName="BeginIfCommand" IsCommented="false" SelectionName="If - Begin If" DefaultPause="250" LineNumber="2" PauseBeforeExeucution="false" CommandEnabled="true" v_IfActionType="Value">
        <v_IfActionParameterTable>
          <xs:schema id="NewDataSet" xmlns="" xmlns:xs="http://www.w3.org/2001/XMLSchema" xmlns:msdata="urn:schemas-microsoft-com:xml-msdata">
            <xs:element name="I8AcPionPara41Table122117.094101">
              <xs:complexType>
                <xs:sequence>
                  <xs:element name="Parameter_x0020_Name" type="xs:string" minOccurs="0" />
                  <xs:element name="Parameter_x0020_Value" type="xs:string" minOccurs="0" />
                </xs:sequence>
              </xs:complexType>
            </xs:element>
            <xs:element name="NewDataSet" msdata:IsDataSet="true" msdata:MainDataTable="I8AcPionPara41Table122117.094101" msdata:UseCurrentLocale="true">
              <xs:complexType>
                <xs:choice minOccurs="0" maxOccurs="unbounded">
                  <xs:element ref="I8AcPionPara41Table122117.094101" />
                </xs:choice>
              </xs:complexType>
            </xs:element>
          </xs:schema>
          <diffgr:diffgram xmlns:msdata="urn:schemas-microsoft-com:xml-msdata" xmlns:diffgr="urn:schemas-microsoft-com:xml-diffgram-v1">
            <DocumentElement>
              <I8AcPionPara41Table122117.094101 diffgr:id="I8AcPionPara41Table122117.0941011" msdata:rowOrder="0" diffgr:hasChanges="inserted">
                <Parameter_x0020_Name>Value1</Parameter_x0020_Name>
                <Parameter_x0020_Value>[ScouterPowerLevel]</Parameter_x0020_Value>
              </I8AcPionPara41Table122117.094101>
              <I8AcPionPara41Table122117.094101 diffgr:id="I8AcPionPara41Table122117.0941012" msdata:rowOrder="1" diffgr:hasChanges="inserted">
                <Parameter_x0020_Name>Operand</Parameter_x0020_Name>
                <Parameter_x0020_Value>is greater than or equal to</Parameter_x0020_Value>
              </I8AcPionPara41Table122117.094101>
              <I8AcPionPara41Table122117.094101 diffgr:id="I8AcPionPara41Table122117.0941013" msdata:rowOrder="2" diffgr:hasChanges="inserted">
                <Parameter_x0020_Name>Value2</Parameter_x0020_Name>
                <Parameter_x0020_Value>9000</Parameter_x0020_Value>
              </I8AcPionPara41Table122117.094101>
            </DocumentElement>
          </diffgr:diffgram>
        </v_IfActionParameterTable>
      </ScriptCommand>
      <AdditionalScriptCommands>
        <ScriptCommand xsi:type="MessageBoxCommand" CommandName="MessageBoxCommand" IsCommented="false" SelectionName="Message Box - Show Message" DefaultPause="250" LineNumber="3" PauseBeforeExeucution="false" v_Comment="" CommandEnabled="true" v_Message="ITS OVER 9000!!!!!!" v_AutoCloseAfter="0" />
      </AdditionalScriptCommands>
      <AdditionalScriptCommands>
        <ScriptCommand xsi:type="ElseCommand" CommandName="ElseCommand" IsCommented="false" SelectionName="If - Else" DefaultPause="0" LineNumber="4" PauseBeforeExeucution="false" CommandEnabled="true" />
      </AdditionalScriptCommands>
      <AdditionalScriptCommands>
        <ScriptCommand xsi:type="MessageBoxCommand" CommandName="MessageBoxCommand" IsCommented="false" SelectionName="Message Box - Show Message" DefaultPause="250" LineNumber="5" PauseBeforeExeucution="false" v_Comment="" CommandEnabled="true" v_Message="NOT!!!!" v_AutoCloseAfter="0" />
      </AdditionalScriptCommands>
      <AdditionalScriptCommands>
        <ScriptCommand xsi:type="EndIfCommand" CommandName="EndIfCommand" IsCommented="false" SelectionName="If - End If" DefaultPause="0" LineNumber="6" PauseBeforeExeucution="false" CommandEnabled="true" />
      </AdditionalScriptCommands>
    </ScriptAction>
  </Commands>
  <Variables>
    <ScriptVariable>
      <currentPosition>0</currentPosition>
      <variableName>ScouterPowerLevel</variableName>
    </ScriptVariable>
    <ScriptVariable>
      <currentPosition>0</currentPosition>
      <variableName>PowerLevel</variableName>
    </ScriptVariable>
  </Variables>
</Script>